wfmplan/__init__.py
wfmplan/AgentOptimizer/BatchOptimizer.py
wfmplan/AgentOptimizer/Optimizer.py
wfmplan/AgentOptimizer/__init__.py
wfmplan-1.2.2.dist-info/LICENSE.txt
wfmplan-1.2.2.dist-info/METADATA
wfmplan-1.2.2.dist-info/WHEEL
wfmplan-1.2.2.dist-info/entry_points.txt
wfmplan-1.2.2.dist-info/top_level.txt
wfmplan-1.2.2.dist-info/RECORD
