Metadata-Version: 2.1
Name: wfmplan
Version: 1.2.2
Summary: Optimization library for workforce management planning
Home-page: https://github.com/laddha-rishi/wfmplan
Author: Rishi Laddha
Author-email: laddha.rishi@gmail.com
License: MIT
Project-URL: Source Code, https://github.com/laddha-rishi/wfmplan
Project-URL: Documentation, https://medium.com/@laddha.rishi/queueing-up-success-revolutionize-workforce-planning-with-python-6c9d7edbb6cd
Keywords: workforce management optimization
Classifier: License :: OSI Approved :: MIT License
Classifier: Programming Language :: Python :: 3
Classifier: Programming Language :: Python :: 3.8
Classifier: Programming Language :: Python :: 3.9
Classifier: Programming Language :: Python :: 3.10
Classifier: Programming Language :: Python :: 3.11
Requires-Python: >=3.7.12
License-File: LICENSE.txt
Requires-Dist: numpy >=1.21.6
Requires-Dist: pandas >=1.3.5
